jupyter_templates/__init__.py
jupyter_templates/extension.py
jupyter_templates/extension/install.json
jupyter_templates/extension/jupyter_templates.json
jupyter_templates/extension/notebook_templates/jupyterlab_templates/Sample.ipynb
jupyter_templates/labextension/package.json
jupyter_templates/labextension/static/509.752050c3c40f6995ffdf.js
jupyter_templates/labextension/static/remoteEntry.da877696c2084604af02.js
jupyter_templates/labextension/static/style.js
jupyter_templates/labextension/static/third-party-licenses.json
jupyter_templates/nbextension/__init__.py
jupyter_templates/templates/jupyter_templates/Sample.ipynb
jupyter_templates/tests/__init__.py
jupyter_templates/tests/test_all.py
jupyter_templates/tests/test_extension.py
jupyter_templates/tests/test_init.py
jupyter_templates-0.1.1.data/data/share/jupyter/notebook/jupyterlab_templates/Sample.ipynb
jupyter_templates-0.1.1.data/data/etc/jupyter/jupyter_server_config.d/jupyter_templates.json
jupyter_templates-0.1.1.data/data/share/jupyter/labextensions/jupyter_templates/package.json
jupyter_templates-0.1.1.data/data/share/jupyter/labextensions/jupyter_templates/static/509.752050c3c40f6995ffdf.js
jupyter_templates-0.1.1.data/data/share/jupyter/labextensions/jupyter_templates/static/remoteEntry.da877696c2084604af02.js
jupyter_templates-0.1.1.data/data/share/jupyter/labextensions/jupyter_templates/static/style.js
jupyter_templates-0.1.1.data/data/share/jupyter/labextensions/jupyter_templates/static/third-party-licenses.json
jupyter_templates-0.1.1.data/data/share/jupyter/nbextensions/jupyter_templates/icon.svg
jupyter_templates-0.1.1.data/data/share/jupyter/nbextensions/jupyter_templates/main.js
jupyter_templates-0.1.1.data/data/share/jupyter/labextensions/jupyter_templates/install.json
jupyter_templates-0.1.1.dist-info/METADATA
jupyter_templates-0.1.1.dist-info/WHEEL
jupyter_templates-0.1.1.dist-info/licenses/LICENSE
jupyter_templates-0.1.1.dist-info/RECORD
