Metadata-Version: 2.3
Name: jupyter_templates
Version: 0.1.1
Summary: notebook templates for jupyter and jupyterlab
Project-URL: Repository, https://github.com/timkpaine/jupyter_templates
Project-URL: Homepage, https://github.com/timkpaine/jupyter_templates
Author: the jupyter_templates authors
License:                                  Apache License
License-File: LICENSE
Keywords: Jupyter,JupyterLab,JupyterLab Extension,Templates
Classifier: Development Status :: 4 - Beta
Classifier: Framework :: Jupyter
Classifier: Framework :: Jupyter :: JupyterLab
Classifier: License :: OSI Approved :: Apache Software License
Classifier: Programming Language :: Python
Classifier: Programming Language :: Python :: 3
Classifier: Programming Language :: Python :: 3.8
Classifier: Programming Language :: Python :: 3.9
Classifier: Programming Language :: Python :: 3.10
Classifier: Programming Language :: Python :: 3.11
Classifier: Programming Language :: Python :: 3.12
Requires-Python: >=3.7
Requires-Dist: jupyterlab<5,>=4
Provides-Extra: develop
Requires-Dist: check-manifest; extra == 'develop'
Requires-Dist: pytest; extra == 'develop'
Requires-Dist: pytest-cov; extra == 'develop'
Requires-Dist: ruff<0.5,>=0.3; extra == 'develop'
Requires-Dist: twine<5.2,>=5; extra == 'develop'
Provides-Extra: test
Requires-Dist: pytest; extra == 'test'
Requires-Dist: pytest-cov; extra == 'test'
